Marvel_package_rin/__init__.py
Marvel_package_rin/activity4.py
Marvel_package_rin/activity4_5.py
Marvel_package_rin/api.py
Marvel_package_rin/createDF.py
Marvel_package_rin/func_available.py
Marvel_package_rin-0.1.dist-info/METADATA
Marvel_package_rin-0.1.dist-info/WHEEL
Marvel_package_rin-0.1.dist-info/top_level.txt
Marvel_package_rin-0.1.dist-info/RECORD
